[{"numconto":"183c03ef-6aab-407e-b42c-95b7ceb04e7c","via":"7907 Nikki Rue","citta":"La Crosse","provincia":"New Jersey","cap":"08816","stato":"Bermuda","note":"Enim quam et rem odio pariatur molestias repellat."},{"numconto":"f73f316c-83f0-4e0d-a9de-7d8955a9f732","via":"47688 Beth Estate","citta":"Houston","provincia":"North Dakota","cap":"86427-7067","stato":"Swaziland","note":"Et ipsum delectus illum eos distinctio tenetur magnam alias quod."},{"numconto":"183c03ef-6aab-407e-b42c-95b7ceb04e7c","via":"14456 Ferry Fields","citta":"Garden Grove","provincia":"California","cap":"31812-5677","stato":"United States of America","note":"Tempora soluta consequatur voluptatem dolor saepe sed amet."},{"numconto":"d278acc1-9c80-4ca1-be9a-a5d37160b2b0","via":"07589 Brennan Manor","citta":"Waldorf","provincia":"Tennessee","cap":"70525-9319","stato":"United States of America","note":"Saepe modi nam optio nobis."},{"numconto":"34ed1ada-8953-40bd-8071-e0c119a44a0f","via":"900 Maximilian Loaf","citta":"Pine Bluff","provincia":"Kansas","cap":"51012-6694","stato":"Niue","note":"Ut porro temporibus quia ut."}]